prune/__init__.py
prune/__main__.py
gitsaw-0.0.2.dist-info/LICENSE.txt
gitsaw-0.0.2.dist-info/METADATA
gitsaw-0.0.2.dist-info/WHEEL
gitsaw-0.0.2.dist-info/entry_points.txt
gitsaw-0.0.2.dist-info/top_level.txt
gitsaw-0.0.2.dist-info/RECORD
