Metadata-Version: 2.1
Name: gitsaw
Version: 0.0.2
Summary: Add a short description here!
Author: Mads Andreasen
Author-email: github@andreasen.cc
License: MIT
Platform: any
Classifier: Development Status :: 4 - Beta
Classifier: Programming Language :: Python
License-File: LICENSE.txt
Requires-Dist: GitPython
Requires-Dist: inquirer
Requires-Dist: importlib-metadata ; python_version < "3.8"
Provides-Extra: testing
Requires-Dist: setuptools ; extra == 'testing'
Requires-Dist: pytest ; extra == 'testing'
